CHANGES.txt
MANIFEST.in
README.md
requirements.txt
setup.py
wheelcms_theme_bootswatch/__init__.py
wheelcms_theme_bootswatch/models.py
wheelcms_theme_bootswatch.egg-info/PKG-INFO
wheelcms_theme_bootswatch.egg-info/SOURCES.txt
wheelcms_theme_bootswatch.egg-info/dependency_links.txt
wheelcms_theme_bootswatch.egg-info/namespace_packages.txt
wheelcms_theme_bootswatch.egg-info/not-zip-safe
wheelcms_theme_bootswatch.egg-info/requires.txt
wheelcms_theme_bootswatch.egg-info/top_level.txt
wheelcms_theme_bootswatch/static/css/amelia-bootstrap.min.css
wheelcms_theme_bootswatch/static/css/cerulean-bootstrap.min.css
wheelcms_theme_bootswatch/static/css/cosmo-bootstrap.min.css
wheelcms_theme_bootswatch/static/css/cyborg-bootstrap.min.css
wheelcms_theme_bootswatch/static/css/flatly-bootstrap.min.css
wheelcms_theme_bootswatch/static/css/journal-bootstrap.min.css
wheelcms_theme_bootswatch/static/css/readable-bootstrap.min.css
wheelcms_theme_bootswatch/static/css/simplex-bootstrap.min.css
wheelcms_theme_bootswatch/static/css/slate-bootstrap.min.css
wheelcms_theme_bootswatch/static/css/spacelab-bootstrap.min.css
wheelcms_theme_bootswatch/static/css/united-bootstrap.min.css
wheelcms_theme_bootswatch/tests/__init__.py
wheelcms_theme_bootswatch/tests/test_themes.py