Metadata-Version: 1.1
Name: wheelcms-theme-bootswatch
Version: 0.9
Summary: WheelCMS bootswatch.com themes
Home-page: http://github.com/wheelcms/wheelcms_theme_bootswatch
Author: Ivo van der Wijk
Author-email: wheelcms@in.m3r.nl
License: BSD
Platform: UNKNOWN
Classifier: Programming Language :: Python
